LICENSE
README.md
setup.py
aem_xss.egg-info/PKG-INFO
aem_xss.egg-info/SOURCES.txt
aem_xss.egg-info/dependency_links.txt
aem_xss.egg-info/entry_points.txt
aem_xss.egg-info/requires.txt
aem_xss.egg-info/top_level.txt
aemxss/main.py
aemxss/includes/__init__.py
aemxss/includes/bot.py
aemxss/includes/filereader.py
aemxss/includes/scan.py
aemxss/includes/writefile.py
aemxss/utils/__init__.py
aemxss/utils/configure.py
aemxss/utils/const.py
aemxss/utils/helpers.py
aemxss/utils/status.py